csv2drf/__init__.py
csv2drf/csv2drf.py
csv2drf-4.7.0.dist-info/METADATA
csv2drf-4.7.0.dist-info/WHEEL
csv2drf-4.7.0.dist-info/entry_points.txt
csv2drf-4.7.0.dist-info/RECORD
